pipey/__init__.py
pipey/base.py
pipey/extended.py
pipey/tests/__init__.py
pipey/tests/fixtures.py
pipey/tests/test_base.py
pipey/tests/test_extended.py
pipey/tests/utils.py
pipey-0.0.1a4.dist-info/METADATA
pipey-0.0.1a4.dist-info/RECORD
pipey-0.0.1a4.dist-info/WHEEL
pipey-0.0.1a4.dist-info/top_level.txt
