Metadata-Version: 2.1
Name: pipey
Version: 0.0.1a4
Summary: Declarative syntactic sugar that enables piping in python.
Home-page: https://github.com/dataframehq/pipey
Author: Joseph Moon
Author-email: joseph@opendataframe.com
License: GPLv3
Keywords: pipe,declarative,python,data science
Platform: UNKNOWN
